hexdomain.py
hexdomain-1.0.0.dist-info/DESCRIPTION.rst
hexdomain-1.0.0.dist-info/METADATA
hexdomain-1.0.0.dist-info/RECORD
hexdomain-1.0.0.dist-info/WHEEL
hexdomain-1.0.0.dist-info/entry_points.txt
hexdomain-1.0.0.dist-info/metadata.json
hexdomain-1.0.0.dist-info/top_level.txt
