Metadata-Version: 2.0
Name: hexdomain
Version: 1.0.0
Summary: Generate domain names that only contain hexadecimal numbers.
Home-page: https://github.com/benwebber/hexdomain/
Author: Ben Webber
Author-email: benjamin.webber@gmail.com
License: UNKNOWN
Platform: UNKNOWN
Classifier: Development Status :: 5 - Production/Stable
Classifier: Programming Language :: Python :: 2
Classifier: Programming Language :: Python :: 2.7
Classifier: Programming Language :: Python :: 3
Classifier: Programming Language :: Python :: 3.4
Classifier: Programming Language :: Python :: 3.5
Requires-Dist: six
Requires-Dist: tld
